h5_models/__init__.py
midis/__init__.py
polymuse/__init__.py
polymuse/builder.py
polymuse/constant.py
polymuse/dataset.py
polymuse/dataset2.py
polymuse/drawer.py
polymuse/dutils.py
polymuse/enc_deco.py
polymuse/evaluation.py
polymuse/generator.py
polymuse/multi_track.py
polymuse/pattern.py
polymuse/player.py
polymuse/rnn.py
polymuse/rnn_h.py
polymuse/rnn_player.py
polymuse/transformer.py
polymuse-0.0.1.dist-info/LICENSE
polymuse-0.0.1.dist-info/METADATA
polymuse-0.0.1.dist-info/WHEEL
polymuse-0.0.1.dist-info/top_level.txt
polymuse-0.0.1.dist-info/RECORD
