Metadata-Version: 2.1
Name: polymuse
Version: 0.0.1
Summary: Polymuse
Home-page: https://github.com/rushike/polymuse-future
Author: rushike
Author-email: rushike.ab1@gmail.com
License: UNKNOWN
Platform: UNKNOWN
Classifier: Programming Language :: Python :: 3
Classifier: License :: OSI Approved :: MIT License
Classifier: Operating System :: OS Independent
Requires-Dist: numpy
Requires-Dist: magenta
Requires-Dist: keras
